ugbio_single_cell/collect_statistics.py
ugbio_single_cell/create_plots.py
ugbio_single_cell/sc_qc_dataclasses.py
ugbio_single_cell/single_cell_qc_pipeline.py
ugbio_single_cell/reports/single_cell_qc_report.ipynb
ugbio_single_cell-1.20.0.dist-info/METADATA
ugbio_single_cell-1.20.0.dist-info/WHEEL
ugbio_single_cell-1.20.0.dist-info/entry_points.txt
ugbio_single_cell-1.20.0.dist-info/top_level.txt
ugbio_single_cell-1.20.0.dist-info/RECORD
