Metadata-Version: 2.4
Name: ugbio_single_cell
Version: 1.20.0
Summary: Ultima Genomics Single Cell utils
Author-email: Inbal Zelig <inbal.zelig@ultimagen.com>
Requires-Python: >=3.11
Requires-Dist: ugbio_core[reports]
Requires-Dist: bio>=1.7.1
